authorizenet_python/__init__.py
authorizenet_python/api/__init__.py
authorizenet_python/api/models/__init__.py
authorizenet_python-0.0.1.dist-info/METADATA
authorizenet_python-0.0.1.dist-info/WHEEL
authorizenet_python-0.0.1.dist-info/top_level.txt
authorizenet_python-0.0.1.dist-info/RECORD
